covid19/__init__.py
covid19.py-0.0.1.data/scripts/covid19.py
covid19.py-0.0.1.dist-info/COPYING
covid19.py-0.0.1.dist-info/METADATA
covid19.py-0.0.1.dist-info/WHEEL
covid19.py-0.0.1.dist-info/top_level.txt
covid19.py-0.0.1.dist-info/RECORD
